priority/__init__.py
priority/priority.py
priority-1.2.2.dist-info/DESCRIPTION.rst
priority-1.2.2.dist-info/METADATA
priority-1.2.2.dist-info/RECORD
priority-1.2.2.dist-info/WHEEL
priority-1.2.2.dist-info/metadata.json
priority-1.2.2.dist-info/top_level.txt
